mpremote/__init__.py
mpremote/__main__.py
mpremote/commands.py
mpremote/console.py
mpremote/main.py
mpremote/mip.py
mpremote/mp_errno.py
mpremote/repl.py
mpremote/romfs.py
mpremote/transport.py
mpremote/transport_serial.py
mpremote-1.26.0.dist-info/METADATA
mpremote-1.26.0.dist-info/WHEEL
mpremote-1.26.0.dist-info/entry_points.txt
mpremote-1.26.0.dist-info/licenses/LICENSE
mpremote-1.26.0.dist-info/RECORD
