Metadata-Version: 2.4
Name: mpremote
Version: 1.26.0
Summary: Tool for interacting remotely with MicroPython devices
Project-URL: Homepage, https://github.com/micropython/micropython
Author-email: Damien George <damien@micropython.org>
License: MIT
License-File: LICENSE
Keywords: hardware,micropython
Classifier: Intended Audience :: Developers
Classifier: License :: OSI Approved :: MIT License
Classifier: Operating System :: OS Independent
Classifier: Programming Language :: Python :: 3
Classifier: Topic :: Software Development :: Embedded Systems
Classifier: Topic :: System :: Hardware
Requires-Python: >=3.4
Requires-Dist: importlib-metadata>=1.4; python_version < '3.8'
Requires-Dist: platformdirs>=4.3.7
Requires-Dist: pyserial>=3.3
